.gitignore
AUTHORS.rst
LICENSE
README.rst
VERSION
setup.cfg
setup.py
djangopypi2/__init__.py
djangopypi2/manage_pypi_site.py
djangopypi2/urls.py
djangopypi2.egg-info/PKG-INFO
djangopypi2.egg-info/SOURCES.txt
djangopypi2.egg-info/dependency_links.txt
djangopypi2.egg-info/entry_points.txt
djangopypi2.egg-info/not-zip-safe
djangopypi2.egg-info/requires.txt
djangopypi2.egg-info/top_level.txt
djangopypi2/apps/__init__.py
djangopypi2/apps/pypi_frontend/__init__.py
djangopypi2/apps/pypi_frontend/admin.py
djangopypi2/apps/pypi_frontend/basic_auth.py
djangopypi2/apps/pypi_frontend/distutils_request.py
djangopypi2/apps/pypi_frontend/distutils_views.py
djangopypi2/apps/pypi_frontend/models.py
djangopypi2/apps/pypi_frontend/search_indexes.py
djangopypi2/apps/pypi_frontend/signals.py
djangopypi2/apps/pypi_frontend/urls.py
djangopypi2/apps/pypi_frontend/utils.py
djangopypi2/apps/pypi_frontend/views.py
djangopypi2/apps/pypi_frontend/xmlrpc_views.py
djangopypi2/apps/pypi_frontend/fixtures/initial.json
djangopypi2/apps/pypi_frontend/templates/pypi_frontend/package_detail_simple.html
djangopypi2/apps/pypi_frontend/templates/pypi_frontend/package_doap.xml
djangopypi2/apps/pypi_frontend/templates/pypi_frontend/package_list_simple.html
djangopypi2/apps/pypi_frontend/templates/pypi_frontend/release_doap.xml
djangopypi2/apps/pypi_frontend/templates/pypi_frontend/release_doap_fragment.xml
djangopypi2/apps/pypi_frontend/templates/pypi_frontend/haystack/package_text.txt
djangopypi2/apps/pypi_frontend/templatetags/__init__.py
djangopypi2/apps/pypi_frontend/templatetags/safemarkup.py
djangopypi2/apps/pypi_manage/__init__.py
djangopypi2/apps/pypi_manage/admin.py
djangopypi2/apps/pypi_manage/models.py
djangopypi2/apps/pypi_manage/urls.py
djangopypi2/apps/pypi_manage/views.py
djangopypi2/apps/pypi_manage/templates/pypi_manage/base.html
djangopypi2/apps/pypi_manage/templates/pypi_manage/forbidden.html
djangopypi2/apps/pypi_manage/templates/pypi_manage/index.html
djangopypi2/apps/pypi_metadata/__init__.py
djangopypi2/apps/pypi_metadata/admin.py
djangopypi2/apps/pypi_metadata/definitions.py
djangopypi2/apps/pypi_metadata/forms.py
djangopypi2/apps/pypi_metadata/models.py
djangopypi2/apps/pypi_metadata/urls.py
