Metadata-Version: 1.1
Name: djangopypi2
Version: 0.6.1
Summary: A Django application that emulates the Python Package Index.
Home-page: http://github.com/popen2/djangopypi2
Author: Zohar Zilberman
Author-email: popen2@gmail.com
License: BSD
Keywords: django pypi packaging index
Platform: UNKNOWN
Classifier: Framework :: Django
Classifier: Development Status :: 4 - Beta
Classifier: Programming Language :: Python
Classifier: Environment :: Web Environment
Classifier: Operating System :: OS Independent
Classifier: Intended Audience :: Developers
Classifier: Intended Audience :: System Administrators
Classifier: License :: OSI Approved :: BSD License
Classifier: Topic :: System :: Software Distribution
Classifier: Programming Language :: Python
Classifier: Topic :: Software Development :: Libraries :: Python Modules
